datasette_saved_queries/__init__.py
datasette_saved_queries-0.2.2.dist-info/METADATA
datasette_saved_queries-0.2.2.dist-info/WHEEL
datasette_saved_queries-0.2.2.dist-info/entry_points.txt
datasette_saved_queries-0.2.2.dist-info/top_level.txt
datasette_saved_queries-0.2.2.dist-info/RECORD
