Metadata-Version: 2.1
Name: datasette-saved-queries
Version: 0.2.2
Summary: Datasette plugin that lets users save and execute queries
Home-page: https://github.com/simonw/datasette-saved-queries
Author: Simon Willison
License: Apache License, Version 2.0
Project-URL: Issues, https://github.com/simonw/datasette-saved-queries/issues
Project-URL: CI, https://github.com/simonw/datasette-saved-queries/actions
Project-URL: Changelog, https://github.com/simonw/datasette-saved-queries/releases
Requires-Dist: datasette >=0.45
Requires-Dist: sqlite-utils
Provides-Extra: test
Requires-Dist: pytest ; extra == 'test'
Requires-Dist: pytest-asyncio ; extra == 'test'
Requires-Dist: httpx ; extra == 'test'
